AUTHORS.rst
CONTRIBUTING.rst
HISTORY.rst
LICENSE
MANIFEST.in
README.rst
setup.py
docs/Makefile
docs/authors.rst
docs/conf.py
docs/contributing.rst
docs/history.rst
docs/index.rst
docs/installation.rst
docs/make.bat
docs/readme.rst
docs/usage.rst
tests/__init__.py
tests/test_usdt.py
usdt/__init__.py
usdt/build_hooks.py
usdt/log.py
usdt/tracer.py
usdt.egg-info/PKG-INFO
usdt.egg-info/SOURCES.txt
usdt.egg-info/dependency_links.txt
usdt.egg-info/not-zip-safe
usdt.egg-info/top_level.txt
usdt/libusdt/.git
usdt/libusdt/.gitignore
usdt/libusdt/LICENCE
usdt/libusdt/Makefile
usdt/libusdt/README.md
usdt/libusdt/libusdt.a
usdt/libusdt/test.pl
usdt/libusdt/test_mem_usage.c
usdt/libusdt/test_usdt.c
usdt/libusdt/test_usdt.o
usdt/libusdt/test_usdt32
usdt/libusdt/test_usdt64
usdt/libusdt/usdt.c
usdt/libusdt/usdt.h
usdt/libusdt/usdt.o
usdt/libusdt/usdt_dof.c
usdt/libusdt/usdt_dof.o
usdt/libusdt/usdt_dof_file.c
usdt/libusdt/usdt_dof_file.o
usdt/libusdt/usdt_dof_sections.c
usdt/libusdt/usdt_dof_sections.o
usdt/libusdt/usdt_internal.h
usdt/libusdt/usdt_probe.c
usdt/libusdt/usdt_probe.o
usdt/libusdt/usdt_tracepoints.o
usdt/libusdt/usdt_tracepoints_i386.o
usdt/libusdt/usdt_tracepoints_i386.s
usdt/libusdt/usdt_tracepoints_x86_64.o
usdt/libusdt/usdt_tracepoints_x86_64.s