Metadata-Version: 1.1
Name: usdt
Version: 0.1.4
Summary: Python libusdt bindings
Home-page: https://github.com/nshalman/python-usdt
Author: Nahum Shalman
Author-email: nshalman@omniti.com
License: BSD
Keywords: usdt
Platform: UNKNOWN
Classifier: Development Status :: 2 - Pre-Alpha
Classifier: Intended Audience :: Developers
Classifier: License :: OSI Approved :: BSD License
Classifier: Natural Language :: English
Classifier: Programming Language :: Python :: 2
Classifier: Programming Language :: Python :: 2.6
Classifier: Programming Language :: Python :: 2.7
Classifier: Programming Language :: Python :: 3
Classifier: Programming Language :: Python :: 3.3
